rets/__init__.py
rets/errors.py
rets/client/__init__.py
rets/client/client.py
rets/client/decoder.py
rets/client/object_type.py
rets/client/record.py
rets/client/resource.py
rets/client/resource_class.py
rets/client/utils.py
rets/http/__init__.py
rets/http/client.py
rets/http/data.py
rets/http/parsers/__init__.py
rets/http/parsers/parse.py
rets/http/parsers/parse_object.py
properly_rets-1.0.26.dist-info/LICENSE.md
properly_rets-1.0.26.dist-info/METADATA
properly_rets-1.0.26.dist-info/WHEEL
properly_rets-1.0.26.dist-info/top_level.txt
properly_rets-1.0.26.dist-info/RECORD
