Metadata-Version: 2.1
Name: properly-rets
Version: 1.0.26
Summary: properly-rets
Home-page: https://github.com/goproperly/rets
Author: GoProperly
Author-email: info@goproperly.com
License: MIT License
Platform: UNKNOWN
Classifier: Intended Audience :: Developers
Classifier: Intended Audience :: Financial and Insurance Industry
Classifier: Intended Audience :: Information Technology
Classifier: Intended Audience :: Other Audience
Classifier: License :: OSI Approved :: MIT License
Classifier: Natural Language :: English
Classifier: Operating System :: OS Independent
Classifier: Programming Language :: Python
Classifier: Programming Language :: Python :: 3
Classifier: Programming Language :: Python :: 3.5
Classifier: Programming Language :: Python :: 3.6
Classifier: Programming Language :: Python :: 3 :: Only
Classifier: Programming Language :: Python :: Implementation :: CPython
Classifier: Programming Language :: Python :: Implementation :: PyPy
Classifier: Topic :: Internet :: WWW/HTTP
Classifier: Topic :: Internet :: WWW/HTTP :: Indexing/Search
Requires-Dist: requests (>=2.12.3)
Requires-Dist: requests-toolbelt (!=0.9.0,>=0.7.0)
Requires-Dist: udatetime (==0.0.16)
Requires-Dist: docopts
Requires-Dist: lxml (>=4.3.0)
Requires-Dist: twine
